useful_decoration/__init__.py
useful_decoration/decorations.py
useful_decoration/func.py
useful_decoration/func_callable.py
useful_decoration/func_para.py
useful_decoration/single.py
useful_decoration/timer.py
useful_decoration-1.1.5.dist-info/LICENSE.txt
useful_decoration-1.1.5.dist-info/METADATA
useful_decoration-1.1.5.dist-info/WHEEL
useful_decoration-1.1.5.dist-info/top_level.txt
useful_decoration-1.1.5.dist-info/RECORD
