Metadata-Version: 2.1
Name: useful-decoration
Version: 1.1.5
Summary: powerful and useful decorations
Home-page: https://github.com/changyubiao/useful_decoration
Author: frank
Author-email: 15769162764@163.com
License: Apache License 2.0
Project-URL: Documentation, https://useful-decoration.readthedocs.io/en/latest/
Project-URL: Code, https://github.com/changyubiao/useful_decoration
Platform: UNKNOWN
Classifier: Development Status :: 3 - Alpha
Classifier: Intended Audience :: Developers
Classifier: Topic :: Software Development :: Build Tools
Classifier: License :: OSI Approved :: MIT License
Classifier: Programming Language :: Python :: 2.7
Classifier: Programming Language :: Python :: 3
Classifier: Programming Language :: Python :: 3.2
Classifier: Programming Language :: Python :: 3.3
Classifier: Programming Language :: Python :: 3.4
Classifier: Programming Language :: Python :: 3.5
Classifier: Programming Language :: Python :: 3.6
Classifier: Programming Language :: Python :: 3.7
Requires-Python: >=3.6
Requires-Dist: pysimple-log
